prompt_lockbox/__init__.py
prompt_lockbox/ai/__init__.py
prompt_lockbox/ai/documenter.py
prompt_lockbox/ai/executor.py
prompt_lockbox/ai/improver.py
prompt_lockbox/ai/logging.py
prompt_lockbox/api.py
prompt_lockbox/cli/__init__.py
prompt_lockbox/cli/_ai.py
prompt_lockbox/cli/configure.py
prompt_lockbox/cli/main.py
prompt_lockbox/cli/manage.py
prompt_lockbox/cli/project.py
prompt_lockbox/cli/search.py
prompt_lockbox/core/__init__.py
prompt_lockbox/core/integrity.py
prompt_lockbox/core/project.py
prompt_lockbox/core/prompt.py
prompt_lockbox/core/templating.py
prompt_lockbox/search/__init__.py
prompt_lockbox/search/fuzzy.py
prompt_lockbox/search/hybrid.py
prompt_lockbox/search/splade.py
prompt_lockbox/ui/__init__.py
prompt_lockbox/ui/display.py
prompt_lockbox-0.1.3.dist-info/entry_points.txt
prompt_lockbox-0.1.3.dist-info/LICENSE
prompt_lockbox-0.1.3.dist-info/METADATA
prompt_lockbox-0.1.3.dist-info/WHEEL
prompt_lockbox-0.1.3.dist-info/RECORD
