Metadata-Version: 2.1
Name: prompt-lockbox
Version: 0.1.3
Summary: An AI toolkit to supercharge your prompts.
Author: ananya868
Author-email: ananya8154@gmail.com
Requires-Python: >=3.10,<4.0
Classifier: Programming Language :: Python :: 3
Classifier: Programming Language :: Python :: 3.10
Classifier: Programming Language :: Python :: 3.11
Classifier: Programming Language :: Python :: 3.12
Provides-Extra: all
Provides-Extra: anthropic
Provides-Extra: huggingface
Provides-Extra: ollama
Provides-Extra: openai
Provides-Extra: search
Requires-Dist: anthropic (>=0.25.0,<0.26.0) ; extra == "anthropic" or extra == "all"
Requires-Dist: faiss-cpu (>=1.11.0,<2.0.0) ; extra == "search" or extra == "all"
Requires-Dist: jinja2 (>=3.1.6,<4.0.0)
Requires-Dist: litellm (>=1.74.0.post1,<2.0.0) ; extra == "huggingface" or extra == "all"
Requires-Dist: lunr (>=0.7.0,<0.8.0) ; extra == "search" or extra == "all"
Requires-Dist: mirascope (>=1.25.1,<2.0.0)
Requires-Dist: numpy ; extra == "search" or extra == "all"
Requires-Dist: ollama (>=0.2.0,<0.3.0) ; extra == "ollama" or extra == "all"
Requires-Dist: openai (>=1.88.0,<2.0.0) ; extra == "openai" or extra == "all"
Requires-Dist: packaging (>=24.0,<25.0)
Requires-Dist: pydantic
Requires-Dist: python-dotenv (>=1.0.0,<2.0.0)
Requires-Dist: pyyaml (>=6.0.2,<7.0.0)
Requires-Dist: questionary (>=2.1.0,<3.0.0)
Requires-Dist: scikit-learn ; extra == "search" or extra == "all"
Requires-Dist: scipy ; extra == "search" or extra == "all"
Requires-Dist: sentence-transformers (>=4.1.0,<5.0.0) ; extra == "search" or extra == "all"
Requires-Dist: thefuzz (>=0.22.1,<0.23.0)
Requires-Dist: tomli (>=2.2.1,<3.0.0)
Requires-Dist: tomli-w (>=1.2.0,<2.0.0)
Requires-Dist: torch ; extra == "huggingface" or extra == "all"
Requires-Dist: transformers ; extra == "huggingface" or extra == "all"
Requires-Dist: typer[all] (>=0.16.0,<0.17.0)
Requires-Dist: tzdata (>=2025.2,<2026.0)
Requires-Dist: whoosh (>=2.7.4,<3.0.0) ; extra == "search" or extra == "all"
